vprint/__init__.py
vprint/base256.py
vprint/formatting.py
vprint/loggers.py
vprint/test.py
vprint/version.py
vprint/vprint_level.py
vprint/tests/__init__.py
vprint/tests/really_long_name_for_testing_truncation.py
vprint-0.0.3.dist-info/LICENSE
vprint-0.0.3.dist-info/METADATA
vprint-0.0.3.dist-info/WHEEL
vprint-0.0.3.dist-info/top_level.txt
vprint-0.0.3.dist-info/RECORD
