Metadata-Version: 2.1
Name: vprint
Version: 0.0.3
Summary: Verbose Printing Utility
Home-page: https://github.com/xkortex/vprint
Author: Michael McDermott
License: MIT
Platform: UNKNOWN
